retox/__init__.py
retox/__main__.py
retox/exclude.py
retox/log.py
retox/path.py
retox/proclimit.py
retox/reporter.py
retox/service.py
retox/ui.py
retox/watch.py
retox-1.5.0.dist-info/DESCRIPTION.rst
retox-1.5.0.dist-info/METADATA
retox-1.5.0.dist-info/RECORD
retox-1.5.0.dist-info/WHEEL
retox-1.5.0.dist-info/entry_points.txt
retox-1.5.0.dist-info/metadata.json
retox-1.5.0.dist-info/top_level.txt
