Metadata-Version: 2.0
Name: retox
Version: 1.5.0
Summary: A parallel service for tox
Home-page: https://github.com/tonybaloney/retox
Author: Anthony Shaw
Author-email: UNKNOWN
License: MIT
Platform: unix
Platform: linux
Platform: osx
Platform: cygwin
Platform: win32
Classifier: Development Status :: 4 - Beta
Classifier: Intended Audience :: Developers
Classifier: License :: OSI Approved :: MIT License
Classifier: Operating System :: POSIX
Classifier: Operating System :: Microsoft :: Windows
Classifier: Operating System :: MacOS :: MacOS X
Classifier: Topic :: Software Development :: Testing
Classifier: Topic :: Software Development :: Libraries
Classifier: Topic :: Utilities
Classifier: Programming Language :: Python
Requires-Dist: tox (==2.9.1)
Requires-Dist: eventlet (==0.21.0)
Requires-Dist: asciimatics (==1.9.0)
Requires-Dist: pathlib2 (==2.3.0)
